rhos/__init__.py
rhos/_version.py
rhos-0.1.dist-info/LICENSE.txt
rhos-0.1.dist-info/METADATA
rhos-0.1.dist-info/WHEEL
rhos-0.1.dist-info/top_level.txt
rhos-0.1.dist-info/RECORD
